oxfordapi/__init__.py
oxfordapi/api.py
oxfordapi-0.1.1.dist-info/licenses/LICENSE
oxfordapi-0.1.1.dist-info/METADATA
oxfordapi-0.1.1.dist-info/WHEEL
oxfordapi-0.1.1.dist-info/top_level.txt
oxfordapi-0.1.1.dist-info/RECORD
