Metadata-Version: 2.4
Name: oxfordapi
Version: 0.1.1
Summary: Explore the Oxford dictionaries API.
Requires-Python: >=3.11.0
License-File: LICENSE
Requires-Dist: httpx>=0.28.1
Dynamic: license-file
